broadbean/__init__.py
broadbean/_version.py
broadbean/blueprint.py
broadbean/broadbean.py
broadbean/element.py
broadbean/plotting.py
broadbean/py.typed
broadbean/ripasso.py
broadbean/sequence.py
broadbean/tools.py
broadbean-0.14.0.dist-info/LICENSE
broadbean-0.14.0.dist-info/METADATA
broadbean-0.14.0.dist-info/WHEEL
broadbean-0.14.0.dist-info/top_level.txt
broadbean-0.14.0.dist-info/RECORD
